Workbook

Sheet 1_Financial_Data
A1: TATA CONSULTANCY SERVICES — PROFIT ANALYSIS PROJECT
A2: 5-Year Consolidated Financial Data | FY 2019-20 to FY 2023-24 | All figures in ₹ Crores
A4: COLOR LEGEND:
A5: Blue = Input Data (hardcoded) | B5: Black = Formula / Calculated | C5: Green = Cross-sheet Link
A7: Financial Year | B7: Revenue (₹ Crores) | C7: Operating Profit (₹ Crores) | D7: Net Profit (₹ Crores) | E7: Total Expenses (₹ Crores) | F7: EPS (₹) | G7: Employees | H7: Dividends Paid (₹ Crores) | I7: Tax Paid (₹ Crores)
A8: FY 2019-20 | B8: 156949 | C8: 38327 | D8: 32430 | E8: 118622 | F8: 83.68 | G8: 448464 | H8: 27160 | I8: 7782
A9: FY 2020-21 | B9: 164177 | C9: 41720 | D9: 33388 | E9: 122457 | F9: 90.19 | G9: 488649 | H9: 30003 | I9: 7914
A10: FY 2021-22 | B10: 191754 | C10: 47654 | D10: 38327 | E10: 144100 | F10: 103.6 | G10: 592195 | H10: 34000 | I10: 8867
A11: FY 2022-23 | B11: 225458 | C11: 53553 | D11: 42147 | E11: 171905 | F11: 114.72 | G11: 614795 | H11: 37000 | I11: 10720
A12: FY 2023-24 | B12: 240893 | C12: 63000 | D12: 46099 | E12: 177893 | F12: 124.6 | G12: 601546 | H12: 40000 | I12: 11050
A13: 5-YEAR TOTALS & AVERAGES
A14: TOTAL (5 Years) | B14: =SUM(B8:B12) -> 979231 | C14: =SUM(C8:C12) -> 244254 | D14: =SUM(D8:D12) -> 192391 | E14: =SUM(E8:E12) -> 734977 | F14: =SUM(F8:F12) -> 516.79 | G14: =SUM(G8:G12) -> 2745649 | H14: =SUM(H8:H12) -> 168163 | I14: =SUM(I8:I12) -> 46333
A15: AVERAGE (5 Years) | B15: =AVERAGE(B8:B12) -> 195846.2 | C15: =AVERAGE(C8:C12) -> 48850.8 | D15: =AVERAGE(D8:D12) -> 38478.2 | E15: =AVERAGE(E8:E12) -> 146995.4 | F15: =AVERAGE(F8:F12) -> 103.358 | G15: =AVERAGE(G8:G12) -> 549129.8 | H15: =AVERAGE(H8:H12) -> 33632.6 | I15: =AVERAGE(I8:I12) -> 9266.6
A16: MAX (5 Years) | B16: =MAX(B8:B12) -> 240893 | C16: =MAX(C8:C12) -> 63000 | D16: =MAX(D8:D12) -> 46099 | E16: =MAX(E8:E12) -> 177893 | F16: =MAX(F8:F12) -> 124.6 | G16: =MAX(G8:G12) -> 614795 | H16: =MAX(H8:H12) -> 40000 | I16: =MAX(I8:I12) -> 11050
A17: MIN (5 Years) | B17: =MIN(B8:B12) -> 156949 | C17: =MIN(C8:C12) -> 38327 | D17: =MIN(D8:D12) -> 32430 | E17: =MIN(E8:E12) -> 118622 | F17: =MIN(F8:F12) -> 83.68 | G17: =MIN(G8:G12) -> 448464 | H17: =MIN(H8:H12) -> 27160 | I17: =MIN(I8:I12) -> 7782
A19: Source: TCS Annual Reports FY2020–FY2024 | BSE India (BSE: 532540) | Screener.in | www.tcs.com/investor-relations

Sheet 2_Ratio_Analysis
A1: TATA CONSULTANCY SERVICES — COMPREHENSIVE RATIO ANALYSIS
A2: All ratios calculated using Excel formulas linked to Financial Data sheet
A4: SECTION A — PROFITABILITY RATIOS
A5: Ratio | B5: FY 2019-20 | C5: FY 2020-21 | D5: FY 2021-22 | E5: FY 2022-23 | F5: FY 2023-24 | G5: 5-Yr Avg | H5: Formula Used | I5: Interpretation
A6: 1. Net Profit Margin (%) | B6: ='1_Financial_Data'!D8/'1_Financial_Data'!B8*100 -> 20.662763 | C6: ='1_Financial_Data'!D9/'1_Financial_Data'!B9*100 -> 20.336588 | D6: ='1_Financial_Data'!D10/'1_Financial_Data'!B10*100 -> 19.987588 | E6: ='1_Financial_Data'!D11/'1_Financial_Data'!B11*100 -> 18.693947 | F6: ='1_Financial_Data'!D12/'1_Financial_Data'!B12*100 -> 19.136712 | G6: =AVERAGE(B6:F6) -> 19.76352 | H6: Net Profit / Revenue × 100 | I6: Higher % = more profitable. TCS ~19-21% is excellent for IT sector.
A7: 2. Operating Profit Margin (%) | B7: ='1_Financial_Data'!C8/'1_Financial_Data'!B8*100 -> 24.420035 | C7: ='1_Financial_Data'!C9/'1_Financial_Data'!B9*100 -> 25.411598 | D7: ='1_Financial_Data'!C10/'1_Financial_Data'!B10*100 -> 24.851633 | E7: ='1_Financial_Data'!C11/'1_Financial_Data'!B11*100 -> 23.752983 | F7: ='1_Financial_Data'!C12/'1_Financial_Data'!B12*100 -> 26.15269 | G7: =AVERAGE(B7:F7) -> 24.917788 | H7: Operating Profit / Revenue × 100 | I7: Shows operating efficiency before interest & tax.
A8: 3. Expense Ratio (%) | B8: ='1_Financial_Data'!E8/'1_Financial_Data'!B8*100 -> 75.579965 | C8: ='1_Financial_Data'!E9/'1_Financial_Data'!B9*100 -> 74.588402 | D8: ='1_Financial_Data'!E10/'1_Financial_Data'!B10*100 -> 75.148367 | E8: ='1_Financial_Data'!E11/'1_Financial_Data'!B11*100 -> 76.247017 | F8: ='1_Financial_Data'!E12/'1_Financial_Data'!B12*100 -> 73.84731 | G8: =AVERAGE(B8:F8) -> 75.082212 | H8: Total Expenses / Revenue × 100 | I8: Lower ratio = better cost control. Declining trend is positive.
A9: 4. Gross Profit Margin (%) | B9: =('1_Financial_Data'!B8-'1_Financial_Data'!E8)/'1_Financial_Data'!B8*100 -> 24.420035 | C9: =('1_Financial_Data'!B9-'1_Financial_Data'!E9)/'1_Financial_Data'!B9*100 -> 25.411598 | D9: =('1_Financial_Data'!B10-'1_Financial_Data'!E10)/'1_Financial_Data'!B10*100 -> 24.851633 | E9: =('1_Financial_Data'!B11-'1_Financial_Data'!E11)/'1_Financial_Data'!B11*100 -> 23.752983 | F9: =('1_Financial_Data'!B12-'1_Financial_Data'!E12)/'1_Financial_Data'!B12*100 -> 26.15269 | G9: =AVERAGE(B9:F9) -> 24.917788 | H9: (Revenue - Expenses) / Revenue × 100 | I9: Measures basic profitability before other deductions.
A10: 5. Return on Revenue (%) | B10: ='1_Financial_Data'!D8/'1_Financial_Data'!B8*100 -> 20.662763 | C10: ='1_Financial_Data'!D9/'1_Financial_Data'!B9*100 -> 20.336588 | D10: ='1_Financial_Data'!D10/'1_Financial_Data'!B10*100 -> 19.987588 | E10: ='1_Financial_Data'!D11/'1_Financial_Data'!B11*100 -> 18.693947 | F10: ='1_Financial_Data'!D12/'1_Financial_Data'!B12*100 -> 19.136712 | G10: =AVERAGE(B10:F10) -> 19.76352 | H10: Net Profit / Revenue × 100 | I10: How much net income is earned per ₹ of revenue.
A13: SECTION B — YEAR-ON-YEAR GROWTH RATES (%)
A14: Growth Metric | B14: FY20→21 | C14: FY21→22 | D14: FY22→23 | E14: FY23→24 | F14: 4-Yr CAGR | G14: Best Year | H14: Formula Used | I14: Observation
A15: 1. Revenue Growth (%) | B15: =('1_Financial_Data'!B9-'1_Financial_Data'!B8)/'1_Financial_Data'!B8*100 -> 4.6053177 | C15: =('1_Financial_Data'!B9-'1_Financial_Data'!B8)/'1_Financial_Data'!B8*100 -> 4.6053177 | D15: =('1_Financial_Data'!B10-'1_Financial_Data'!B9)/'1_Financial_Data'!B9*100 -> 16.797115 | E15: =('1_Financial_Data'!B11-'1_Financial_Data'!B10)/'1_Financial_Data'!B10*100 -> 17.576687 | F15: =('1_Financial_Data'!B12/'1_Financial_Data'!B8)^(1/4)-1 -> 0.11305444 | G15: =IF(MAX(B15:E15)=B15,"FY20→21",IF(MAX(B15:E15)=C15,"FY21→22",IF(MAX(B15:E15)=D15,"FY22→23","FY23→24"))) -> FY23→24 | H15: (Current - Previous) / Previous × 100 | I15: Revenue grew consistently YoY; FY22 saw highest jump.
A16: 2. Operating Profit Growth (%) | B16: =('1_Financial_Data'!C9-'1_Financial_Data'!C8)/'1_Financial_Data'!C8*100 -> 8.852767 | C16: =('1_Financial_Data'!C9-'1_Financial_Data'!C8)/'1_Financial_Data'!C8*100 -> 8.852767 | D16: =('1_Financial_Data'!C10-'1_Financial_Data'!C9)/'1_Financial_Data'!C9*100 -> 14.223394 | E16: =('1_Financial_Data'!C11-'1_Financial_Data'!C10)/'1_Financial_Data'!C10*100 -> 12.378814 | F16: =('1_Financial_Data'!C12/'1_Financial_Data'!C8)^(1/4)-1 -> 0.13229328 | G16: =IF(MAX(B16:E16)=B16,"FY20→21",IF(MAX(B16:E16)=C16,"FY21→22",IF(MAX(B16:E16)=D16,"FY22→23","FY23→24"))) -> FY22→23 | H16: (Current - Previous) / Previous × 100 | I16: Operating profit grew faster than revenue in FY24.
A17: 3. Net Profit Growth (%) | B17: =('1_Financial_Data'!D9-'1_Financial_Data'!D8)/'1_Financial_Data'!D8*100 -> 2.9540549 | C17: =('1_Financial_Data'!D9-'1_Financial_Data'!D8)/'1_Financial_Data'!D8*100 -> 2.9540549 | D17: =('1_Financial_Data'!D10-'1_Financial_Data'!D9)/'1_Financial_Data'!D9*100 -> 14.79274 | E17: =('1_Financial_Data'!D11-'1_Financial_Data'!D10)/'1_Financial_Data'!D10*100 -> 9.9668641 | F17: =('1_Financial_Data'!D12/'1_Financial_Data'!D8)^(1/4)-1 -> 0.091908229 | G17: =IF(MAX(B17:E17)=B17,"FY20→21",IF(MAX(B17:E17)=C17,"FY21→22",IF(MAX(B17:E17)=D17,"FY22→23","FY23→24"))) -> FY22→23 | H17: (Current - Previous) / Previous × 100 | I17: Net profit showed stable ~3-15% growth each year.
A18: 4. EPS Growth (%) | B18: =('1_Financial_Data'!F9-'1_Financial_Data'!F8)/'1_Financial_Data'!F8*100 -> 7.7796367 | C18: =('1_Financial_Data'!F9-'1_Financial_Data'!F8)/'1_Financial_Data'!F8*100 -> 7.7796367 | D18: =('1_Financial_Data'!F10-'1_Financial_Data'!F9)/'1_Financial_Data'!F9*100 -> 14.868611 | E18: =('1_Financial_Data'!F11-'1_Financial_Data'!F10)/'1_Financial_Data'!F10*100 -> 10.733591 | F18: =('1_Financial_Data'!F12/'1_Financial_Data'!F8)^(1/4)-1 -> 0.10464846 | G18: =IF(MAX(B18:E18)=B18,"FY20→21",IF(MAX(B18:E18)=C18,"FY21→22",IF(MAX(B18:E18)=D18,"FY22→23","FY23→24"))) -> FY22→23 | H18: (Current - Previous) / Previous × 100 | I18: EPS grew every year — excellent for shareholders.
A19: 5. Employee Growth (%) | B19: =('1_Financial_Data'!G9-'1_Financial_Data'!G8)/'1_Financial_Data'!G8*100 -> 8.9605855 | C19: =('1_Financial_Data'!G9-'1_Financial_Data'!G8)/'1_Financial_Data'!G8*100 -> 8.9605855 | D19: =('1_Financial_Data'!G10-'1_Financial_Data'!G9)/'1_Financial_Data'!G9*100 -> 21.190261 | E19: =('1_Financial_Data'!G11-'1_Financial_Data'!G10)/'1_Financial_Data'!G10*100 -> 3.8163105 | F19: =('1_Financial_Data'!G12/'1_Financial_Data'!G8)^(1/4)-1 -> 0.076180985 | G19: =IF(MAX(B19:E19)=B19,"FY20→21",IF(MAX(B19:E19)=C19,"FY21→22",IF(MAX(B19:E19)=D19,"FY22→23","FY23→24"))) -> FY22→23 | H19: (Current - Previous) / Previous × 100 | I19: Headcount peaked in FY23; FY24 shows rationalisation.
A22: SECTION C — EFFICIENCY RATIOS
A23: Efficiency Metric | B23: FY 2019-20 | C23: FY 2020-21 | D23: FY 2021-22 | E23: FY 2022-23 | F23: FY 2023-24 | G23: 5-Yr Avg | H23: Formula Used | I23: Observation
A24: 1. Revenue per Employee (₹ Cr) | B24: ='1_Financial_Data'!B8/'1_Financial_Data'!G8 -> 0.34997012 | C24: ='1_Financial_Data'!B9/'1_Financial_Data'!G9 -> 0.33598145 | D24: ='1_Financial_Data'!B10/'1_Financial_Data'!G10 -> 0.32380213 | E24: ='1_Financial_Data'!B11/'1_Financial_Data'!G11 -> 0.36672061 | F24: ='1_Financial_Data'!B12/'1_Financial_Data'!G12 -> 0.40045649 | G24: =AVERAGE(B24:F24) -> 0.35538616 | H24: Revenue / No. of Employees | I24: Shows productivity per employee.
A25: 2. Net Profit per Employee (₹ Cr) | B25: ='1_Financial_Data'!D8/'1_Financial_Data'!G8 -> 0.072313497 | C25: ='1_Financial_Data'!D9/'1_Financial_Data'!G9 -> 0.068327163 | D25: ='1_Financial_Data'!D10/'1_Financial_Data'!G10 -> 0.064720236 | E25: ='1_Financial_Data'!D11/'1_Financial_Data'!G11 -> 0.068554559 | F25: ='1_Financial_Data'!D12/'1_Financial_Data'!G12 -> 0.076634206 | G25: =AVERAGE(B25:F25) -> 0.070109932 | H25: Net Profit / No. of Employees | I25: Higher = more profitable per employee.
A26: 3. Op. Profit per Employee (₹ Cr) | B26: ='1_Financial_Data'!C8/'1_Financial_Data'!G8 -> 0.085462824 | C26: ='1_Financial_Data'!C9/'1_Financial_Data'!G9 -> 0.085378257 | D26: ='1_Financial_Data'!C10/'1_Financial_Data'!G10 -> 0.080470115 | E26: ='1_Financial_Data'!C11/'1_Financial_Data'!G11 -> 0.087107084 | F26: ='1_Financial_Data'!C12/'1_Financial_Data'!G12 -> 0.10473015 | G26: =AVERAGE(B26:F26) -> 0.088629685 | H26: Operating Profit / Employees | I26: Reflects operational efficiency per head.
A29: SECTION D — COMPOUND ANNUAL GROWTH RATE (CAGR) SUMMARY
A30: Metric | B30: Start Value (FY20) | C30: End Value (FY24) | D30: No. of Years | E30: CAGR Formula | F30: CAGR Value
A31: Revenue CAGR | B31: ='1_Financial_Data'!B8 -> 156949 | C31: ='1_Financial_Data'!B12 -> 240893 | D31: 4 | E31: (End Value / Start Value)^(1/n) - 1 | F31: =(C31/B31)^(1/D31)-1 -> 0.11305444
A32: Net Profit CAGR | B32: ='1_Financial_Data'!D8 -> 32430 | C32: ='1_Financial_Data'!D12 -> 46099 | D32: 4 | E32: (End Value / Start Value)^(1/n) - 1 | F32: =(C32/B32)^(1/D32)-1 -> 0.091908229
A33: Operating Profit CAGR | B33: ='1_Financial_Data'!C8 -> 38327 | C33: ='1_Financial_Data'!C12 -> 63000 | D33: 4 | E33: (End Value / Start Value)^(1/n) - 1 | F33: =(C33/B33)^(1/D33)-1 -> 0.13229328
A34: EPS CAGR | B34: ='1_Financial_Data'!F8 -> 83.68 | C34: ='1_Financial_Data'!F12 -> 124.6 | D34: 4 | E34: (End Value / Start Value)^(1/n) - 1 | F34: =(C34/B34)^(1/D34)-1 -> 0.10464846

Sheet 3_Growth_Analysis
A1: TATA CONSULTANCY SERVICES — YEAR-ON-YEAR GROWTH & TREND ANALYSIS
A2: Formula: YoY Growth = (Current Year Value − Previous Year Value) / Previous Year Value × 100
A4: ABSOLUTE VALUES (₹ Crores) — Linked from Financial Data Sheet
A5: Metric | B5: FY 2019-20 | C5: FY 2020-21 | D5: FY 2021-22 | E5: FY 2022-23 | F5: FY 2023-24 | G5: Total
A6: Revenue | B6: ='1_Financial_Data'!B8 -> 156949 | C6: ='1_Financial_Data'!B9 -> 164177 | D6: ='1_Financial_Data'!B10 -> 191754 | E6: ='1_Financial_Data'!B11 -> 225458 | F6: ='1_Financial_Data'!B12 -> 240893 | G6: =SUM(B6:F6) -> 979231
A7: Operating Profit | B7: ='1_Financial_Data'!C8 -> 38327 | C7: ='1_Financial_Data'!C9 -> 41720 | D7: ='1_Financial_Data'!C10 -> 47654 | E7: ='1_Financial_Data'!C11 -> 53553 | F7: ='1_Financial_Data'!C12 -> 63000 | G7: =SUM(B7:F7) -> 244254
A8: Net Profit | B8: ='1_Financial_Data'!D8 -> 32430 | C8: ='1_Financial_Data'!D9 -> 33388 | D8: ='1_Financial_Data'!D10 -> 38327 | E8: ='1_Financial_Data'!D11 -> 42147 | F8: ='1_Financial_Data'!D12 -> 46099 | G8: =SUM(B8:F8) -> 192391
A9: Total Expenses | B9: ='1_Financial_Data'!E8 -> 118622 | C9: ='1_Financial_Data'!E9 -> 122457 | D9: ='1_Financial_Data'!E10 -> 144100 | E9: ='1_Financial_Data'!E11 -> 171905 | F9: ='1_Financial_Data'!E12 -> 177893 | G9: =SUM(B9:F9) -> 734977
A11: YEAR-ON-YEAR GROWTH RATES (%) — Formula: (Current−Previous)/Previous×100
A12: Growth Metric | B12: FY 2019-20 (Base) | C12: FY20→21 | D12: FY21→22 | E12: FY22→23 | F12: FY23→24 | G12: Avg Growth
A13: Revenue Growth (%) | B13: Base Year | C13: =(C6-B6)/B6*100 -> 4.6053177 | D13: =(D6-C6)/C6*100 -> 16.797115 | E13: =(E6-D6)/D6*100 -> 17.576687 | F13: =(F6-E6)/E6*100 -> 6.8460645 | G13: =AVERAGE(C13:F13) -> 11.456296
A14: Operating Profit Growth (%) | B14: Base Year | C14: =(C7-B7)/B7*100 -> 8.852767 | D14: =(D7-C7)/C7*100 -> 14.223394 | E14: =(E7-D7)/D7*100 -> 12.378814 | F14: =(F7-E7)/E7*100 -> 17.640468 | G14: =AVERAGE(C14:F14) -> 13.273861
A15: Net Profit Growth (%) | B15: Base Year | C15: =(C8-B8)/B8*100 -> 2.9540549 | D15: =(D8-C8)/C8*100 -> 14.79274 | E15: =(E8-D8)/D8*100 -> 9.9668641 | F15: =(F8-E8)/E8*100 -> 9.3767053 | G15: =AVERAGE(C15:F15) -> 9.2725911
A16: Total Expenses Growth (%) | B16: Base Year | C16: =(C9-B9)/B9*100 -> 3.2329585 | D16: =(D9-C9)/C9*100 -> 17.673959 | E16: =(E9-D9)/D9*100 -> 19.295628 | F16: =(F9-E9)/E9*100 -> 3.4833193 | G16: =AVERAGE(C16:F16) -> 10.921466
A18: CONDITIONAL ANALYSIS — Highest & Lowest Values per Metric
A19: Metric | B19: FY 2019-20 | C19: FY 2020-21 | D19: FY 2021-22 | E19: FY 2022-23 | F19: FY 2023-24 | G19: MAX Year
A20: Revenue | B20: ='1_Financial_Data'!B8 -> 156949 | C20: ='1_Financial_Data'!B9 -> 164177 | D20: ='1_Financial_Data'!B10 -> 191754 | E20: ='1_Financial_Data'!B11 -> 225458 | F20: ='1_Financial_Data'!B12 -> 240893 | G20: =IF(MAX(B20:F20)=B20,"FY20",IF(MAX(B20:F20)=C20,"FY21",IF(MAX(B20:F20)=D20,"FY22",IF(MAX(B20:F20)=E20,"FY23","FY24")))) -> FY24
A21: Operating Profit | B21: ='1_Financial_Data'!C8 -> 38327 | C21: ='1_Financial_Data'!C9 -> 41720 | D21: ='1_Financial_Data'!C10 -> 47654 | E21: ='1_Financial_Data'!C11 -> 53553 | F21: ='1_Financial_Data'!C12 -> 63000 | G21: =IF(MAX(B21:F21)=B21,"FY20",IF(MAX(B21:F21)=C21,"FY21",IF(MAX(B21:F21)=D21,"FY22",IF(MAX(B21:F21)=E21,"FY23","FY24")))) -> FY24
A22: Net Profit | B22: ='1_Financial_Data'!D8 -> 32430 | C22: ='1_Financial_Data'!D9 -> 33388 | D22: ='1_Financial_Data'!D10 -> 38327 | E22: ='1_Financial_Data'!D11 -> 42147 | F22: ='1_Financial_Data'!D12 -> 46099 | G22: =IF(MAX(B22:F22)=B22,"FY20",IF(MAX(B22:F22)=C22,"FY21",IF(MAX(B22:F22)=D22,"FY22",IF(MAX(B22:F22)=E22,"FY23","FY24")))) -> FY24
A23: Total Expenses | B23: ='1_Financial_Data'!E8 -> 118622 | C23: ='1_Financial_Data'!E9 -> 122457 | D23: ='1_Financial_Data'!E10 -> 144100 | E23: ='1_Financial_Data'!E11 -> 171905 | F23: ='1_Financial_Data'!E12 -> 177893 | G23: =IF(MAX(B23:F23)=B23,"FY20",IF(MAX(B23:F23)=C23,"FY21",IF(MAX(B23:F23)=D23,"FY22",IF(MAX(B23:F23)=E23,"FY23","FY24")))) -> FY24
A25: Formula used: IF(MAX(range)=cellX, "Year", ...) to identify peak performance year

Sheet 4_Charts
A1: TATA CONSULTANCY SERVICES — GRAPHICAL TREND ANALYSIS (Charts)
A3: Year | B3: Revenue | C3: Op. Profit | D3: Net Profit | E3: Expenses | F3: EPS
A4: ='1_Financial_Data'!A8 -> FY 2019-20 | B4: ='1_Financial_Data'!B8 -> 156949 | C4: ='1_Financial_Data'!C8 -> 38327 | D4: ='1_Financial_Data'!D8 -> 32430 | E4: ='1_Financial_Data'!E8 -> 118622 | F4: ='1_Financial_Data'!F8 -> 83.68
A5: ='1_Financial_Data'!A9 -> FY 2020-21 | B5: ='1_Financial_Data'!B9 -> 164177 | C5: ='1_Financial_Data'!C9 -> 41720 | D5: ='1_Financial_Data'!D9 -> 33388 | E5: ='1_Financial_Data'!E9 -> 122457 | F5: ='1_Financial_Data'!F9 -> 90.19
A6: ='1_Financial_Data'!A10 -> FY 2021-22 | B6: ='1_Financial_Data'!B10 -> 191754 | C6: ='1_Financial_Data'!C10 -> 47654 | D6: ='1_Financial_Data'!D10 -> 38327 | E6: ='1_Financial_Data'!E10 -> 144100 | F6: ='1_Financial_Data'!F10 -> 103.6
A7: ='1_Financial_Data'!A11 -> FY 2022-23 | B7: ='1_Financial_Data'!B11 -> 225458 | C7: ='1_Financial_Data'!C11 -> 53553 | D7: ='1_Financial_Data'!D11 -> 42147 | E7: ='1_Financial_Data'!E11 -> 171905 | F7: ='1_Financial_Data'!F11 -> 114.72
A8: ='1_Financial_Data'!A12 -> FY 2023-24 | B8: ='1_Financial_Data'!B12 -> 240893 | C8: ='1_Financial_Data'!C12 -> 63000 | D8: ='1_Financial_Data'!D12 -> 46099 | E8: ='1_Financial_Data'!E12 -> 177893 | F8: ='1_Financial_Data'!F12 -> 124.6

Sheet 5_Interpretation
A1: TATA CONSULTANCY SERVICES — FINDINGS, INTERPRETATION & CONCLUSION
A3: KEY PERFORMANCE INDICATORS (Live — auto-calculated from Financial Data)
A4: KPI | B4: FY 2019-20 (Start) | C4: FY 2023-24 (End) | D4: Change (₹ Cr) | E4: Change (%) | F4: CAGR (%) | G4: Assessment
A5: Revenue (₹ Crores) | B5: ='1_Financial_Data'!B8 -> 156949 | C5: ='1_Financial_Data'!B12 -> 240893 | D5: =C5-B5 -> 83944 | E5: =(C5-B5)/B5*100 -> 53.48489 | F5: =(C5/B5)^(1/4)-1 -> 0.11305444 | G5: =IF(F5>0.1,"Excellent ✓",IF(F5>0.05,"Good ✓",IF(F5>0,"Moderate","Review ⚠"))) -> Excellent ✓
A6: Operating Profit (₹ Cr) | B6: ='1_Financial_Data'!C8 -> 38327 | C6: ='1_Financial_Data'!C12 -> 63000 | D6: =C6-B6 -> 24673 | E6: =(C6-B6)/B6*100 -> 64.374984 | F6: =(C6/B6)^(1/4)-1 -> 0.13229328 | G6: =IF(F6>0.1,"Excellent ✓",IF(F6>0.05,"Good ✓",IF(F6>0,"Moderate","Review ⚠"))) -> Excellent ✓
A7: Net Profit (₹ Crores) | B7: ='1_Financial_Data'!D8 -> 32430 | C7: ='1_Financial_Data'!D12 -> 46099 | D7: =C7-B7 -> 13669 | E7: =(C7-B7)/B7*100 -> 42.149245 | F7: =(C7/B7)^(1/4)-1 -> 0.091908229 | G7: =IF(F7>0.1,"Excellent ✓",IF(F7>0.05,"Good ✓",IF(F7>0,"Moderate","Review ⚠"))) -> Good ✓
A8: Total Expenses (₹ Cr) | B8: ='1_Financial_Data'!E8 -> 118622 | C8: ='1_Financial_Data'!E12 -> 177893 | D8: =C8-B8 -> 59271 | E8: =(C8-B8)/B8*100 -> 49.966279 | F8: =(C8/B8)^(1/4)-1 -> 0.10661972 | G8: =IF(F8>0.1,"Excellent ✓",IF(F8>0.05,"Good ✓",IF(F8>0,"Moderate","Review ⚠"))) -> Excellent ✓
A9: EPS (₹) | B9: ='1_Financial_Data'!F8 -> 83.68 | C9: ='1_Financial_Data'!F12 -> 124.6 | D9: =C9-B9 -> 40.92 | E9: =(C9-B9)/B9*100 -> 48.900574 | F9: =(C9/B9)^(1/4)-1 -> 0.10464846 | G9: =IF(F9>0.1,"Excellent ✓",IF(F9>0.05,"Good ✓",IF(F9>0,"Moderate","Review ⚠"))) -> Excellent ✓
A12: PROFITABILITY MARGIN ANALYSIS (Cross-sheet formula: Net Profit / Revenue × 100)
A13: Margin Metric | B13: FY 2019-20 | C13: FY 2020-21 | D13: FY 2021-22 | E13: FY 2022-23 | F13: FY 2023-24 | G13: Trend
A14: Net Profit Margin (%) | B14: ='1_Financial_Data'!D8/'1_Financial_Data'!B8*100 -> 20.662763 | C14: ='1_Financial_Data'!D9/'1_Financial_Data'!B9*100 -> 20.336588 | D14: ='1_Financial_Data'!D10/'1_Financial_Data'!B10*100 -> 19.987588 | E14: ='1_Financial_Data'!D11/'1_Financial_Data'!B11*100 -> 18.693947 | F14: ='1_Financial_Data'!D12/'1_Financial_Data'!B12*100 -> 19.136712 | G14: =IF(F14>B14,"↑ Improving","↓ Declining") -> ↓ Declining
A15: Op. Profit Margin (%) | B15: ='1_Financial_Data'!C8/'1_Financial_Data'!B8*100 -> 24.420035 | C15: ='1_Financial_Data'!C9/'1_Financial_Data'!B9*100 -> 25.411598 | D15: ='1_Financial_Data'!C10/'1_Financial_Data'!B10*100 -> 24.851633 | E15: ='1_Financial_Data'!C11/'1_Financial_Data'!B11*100 -> 23.752983 | F15: ='1_Financial_Data'!C12/'1_Financial_Data'!B12*100 -> 26.15269 | G15: =IF(F15>B15,"↑ Improving","↓ Declining") -> ↑ Improving
A16: Expense Ratio (%) | B16: ='1_Financial_Data'!E8/'1_Financial_Data'!B8*100 -> 75.579965 | C16: ='1_Financial_Data'!E9/'1_Financial_Data'!B9*100 -> 74.588402 | D16: ='1_Financial_Data'!E10/'1_Financial_Data'!B10*100 -> 75.148367 | E16: ='1_Financial_Data'!E11/'1_Financial_Data'!B11*100 -> 76.247017 | F16: ='1_Financial_Data'!E12/'1_Financial_Data'!B12*100 -> 73.84731 | G16: =IF(F16>B16,"↑ Improving","↓ Declining") -> ↓ Declining
A19: KEY FINDINGS & INTERPRETATION
A20: Finding 1 — Revenue Growth
A21: TCS revenue grew from ₹1,56,949 Cr (FY20) to ₹2,40,893 Cr (FY24). The 4-year CAGR of ~11.3% reflects strong and sustained demand for IT services globally. Even during the COVID-19 year (FY21), TCS posted positive growth of 4.6%.
A22: Finding 2 — Profit Consistency
A23: Net Profit grew every single year — from ₹32,430 Cr to ₹46,099 Cr — with a CAGR of ~9.2%. Zero years of profit decline over 5 years demonstrates exceptional financial discipline and earnings quality.
A24: Finding 3 — Margin Stability
A25: Net Profit Margin remained in the 18.7%–20.7% band across all years. Operating Profit Margin improved from 24.4% (FY20) to 26.2% (FY24), reflecting better operational efficiency and scale leverage.
A26: Finding 4 — Cost Management
A27: Despite rising absolute expenses, the Expense Ratio declined from 75.6% in FY20 to 73.9% in FY24. This means TCS generates more revenue per rupee of cost — a sign of operational leverage.
A28: Finding 5 — EPS & Shareholder Value
A29: EPS grew from ₹83.68 to ₹124.60 — a ~48.9% increase over 5 years. Combined with a healthy dividend payout ratio (~84%), TCS has consistently rewarded shareholders, making it a top-tier investment-grade stock.
A31: CONCLUSION
... A34: References: TCS Annual Reports FY2020-FY2024 | BSE India (532540) | Screener.in | Moneycontrol.com
